{
 "as_of": "2026-07-10",
 "budget": "사전 등록 시그널 4종 × 지평 3 — 추가·부활 금지",
 "criteria": "|t|>=2 ∧ 서브기간 3분할 중 2+ 동일 부호 → Phase 3 승격",
 "promoted": [],
 "rows": [
  {
   "signal": "frgn_i20",
   "horizon": "1m",
   "ic": 0.0012,
   "t": 0.06,
   "n": 23,
   "sub_ic": [
    0.0102,
    0.0059,
    -0.0114
   ],
   "sign_consistency": "2/3",
   "promoted": false
  },
  {
   "signal": "frgn_i20",
   "horizon": "3m",
   "ic": -0.0028,
   "t": -0.2,
   "n": 23,
   "sub_ic": [
    -0.0014,
    -0.0065,
    -0.0002
   ],
   "sign_consistency": "3/3",
   "promoted": false
  },
  {
   "signal": "frgn_i20",
   "horizon": "6m",
   "ic": 0.0004,
   "t": 0.03,
   "n": 23,
   "sub_ic": [
    -0.0084,
    -0.0196,
    0.0281
   ],
   "sign_consistency": "1/3",
   "promoted": false
  },
  {
   "signal": "frgn_p20",
   "horizon": "1m",
   "ic": 0.0144,
   "t": 0.82,
   "n": 23,
   "sub_ic": [
    0.0265,
    0.0016,
    0.0166
   ],
   "sign_consistency": "3/3",
   "promoted": false
  },
  {
   "signal": "frgn_p20",
   "horizon": "3m",
   "ic": 0.0054,
   "t": 0.33,
   "n": 23,
   "sub_ic": [
    0.0098,
    -0.0056,
    0.0126
   ],
   "sign_consistency": "2/3",
   "promoted": false
  },
  {
   "signal": "frgn_p20",
   "horizon": "6m",
   "ic": 0.013,
   "t": 0.69,
   "n": 23,
   "sub_ic": [
    0.0016,
    -0.0085,
    0.0444
   ],
   "sign_consistency": "2/3",
   "promoted": false
  },
  {
   "signal": "frgn_i60",
   "horizon": "1m",
   "ic": 0.0086,
   "t": 0.46,
   "n": 23,
   "sub_ic": [
    -0.0113,
    -0.0031,
    0.0378
   ],
   "sign_consistency": "1/3",
   "promoted": false
  },
  {
   "signal": "frgn_i60",
   "horizon": "3m",
   "ic": 0.0158,
   "t": 1.16,
   "n": 23,
   "sub_ic": [
    -0.0027,
    -0.0048,
    0.0526
   ],
   "sign_consistency": "1/3",
   "promoted": false
  },
  {
   "signal": "frgn_i60",
   "horizon": "6m",
   "ic": 0.0057,
   "t": 0.31,
   "n": 23,
   "sub_ic": [
    -0.0187,
    -0.0276,
    0.0604
   ],
   "sign_consistency": "1/3",
   "promoted": false
  },
  {
   "signal": "indiv_i20",
   "horizon": "1m",
   "ic": -0.0022,
   "t": -0.09,
   "n": 23,
   "sub_ic": [
    -0.0385,
    0.0024,
    0.0249
   ],
   "sign_consistency": "1/3",
   "promoted": false
  },
  {
   "signal": "indiv_i20",
   "horizon": "3m",
   "ic": 0.0201,
   "t": 1.1,
   "n": 23,
   "sub_ic": [
    0.0073,
    0.0508,
    0.0008
   ],
   "sign_consistency": "3/3",
   "promoted": false
  },
  {
   "signal": "indiv_i20",
   "horizon": "6m",
   "ic": 0.0175,
   "t": 0.74,
   "n": 23,
   "sub_ic": [
    -0.0061,
    0.069,
    -0.0134
   ],
   "sign_consistency": "1/3",
   "promoted": false
  }
 ],
 "n_snapshots": 23,
 "by_regime_R1": {
  "narrow": {
   "frgn_i20|1m": 0.0692,
   "frgn_p20|1m": 0.0513,
   "frgn_i60|1m": 0.0472,
   "indiv_i20|1m": -0.0381,
   "frgn_i20|3m": -0.0223,
   "frgn_p20|3m": -0.0241,
   "frgn_i60|3m": -0.0207,
   "indiv_i20|3m": 0.0531,
   "frgn_i20|6m": -0.0334,
   "frgn_p20|6m": -0.034,
   "frgn_i60|6m": -0.0361,
   "indiv_i20|6m": 0.0698
  },
  "broad": {
   "frgn_i20|1m": -0.0261,
   "frgn_p20|1m": 0.0043,
   "frgn_i60|1m": -0.0366,
   "indiv_i20|1m": 0.0247,
   "frgn_i20|3m": 0.0069,
   "frgn_p20|3m": 0.0362,
   "frgn_i60|3m": 0.0213,
   "indiv_i20|3m": 0.0226,
   "frgn_i20|6m": 0.0176,
   "frgn_p20|6m": 0.037,
   "frgn_i60|6m": 0.0196,
   "indiv_i20|6m": -0.0177
  },
  "mid": {
   "frgn_i20|1m": -0.0326,
   "frgn_p20|1m": -0.0118,
   "frgn_i60|1m": 0.0391,
   "indiv_i20|1m": -0.0053,
   "frgn_i20|3m": 0.004,
   "frgn_p20|3m": -0.0115,
   "frgn_i60|3m": 0.0492,
   "indiv_i20|3m": -0.0225,
   "frgn_i20|6m": 0.0112,
   "frgn_p20|6m": 0.0278,
   "frgn_i60|6m": 0.0313,
   "indiv_i20|6m": 0.0151
  }
 },
 "per_snapshot": {
  "2019-08-05": {
   "frgn_i20|1m": 0.1062,
   "frgn_p20|1m": 0.1586,
   "frgn_i60|1m": -0.009,
   "indiv_i20|1m": -0.0657,
   "frgn_i20|3m": -0.0201,
   "frgn_p20|3m": 0.0478,
   "frgn_i60|3m": -0.0013,
   "indiv_i20|3m": 0.0558,
   "frgn_i20|6m": 0.0501,
   "frgn_p20|6m": 0.1224,
   "frgn_i60|6m": -0.027,
   "indiv_i20|6m": 0.0903
  },
  "2019-11-07": {
   "frgn_i20|1m": 0.0369,
   "frgn_p20|1m": 0.0086,
   "frgn_i60|1m": 0.0628,
   "indiv_i20|1m": -0.2729,
   "frgn_i20|3m": 0.003,
   "frgn_p20|3m": 0.0556,
   "frgn_i60|3m": 0.0064,
   "indiv_i20|3m": -0.116,
   "frgn_i20|6m": 0.1159,
   "frgn_p20|6m": 0.1018,
   "frgn_i60|6m": 0.0581,
   "indiv_i20|6m": -0.2415
  },
  "2020-02-11": {
   "frgn_i20|1m": 0.1939,
   "frgn_p20|1m": 0.1743,
   "frgn_i60|1m": 0.1359,
   "indiv_i20|1m": -0.1139,
   "frgn_i20|3m": 0.046,
   "frgn_p20|3m": 0.012,
   "frgn_i60|3m": -0.0359,
   "indiv_i20|3m": -0.0322,
   "frgn_i20|6m": -0.012,
   "frgn_p20|6m": 0.0052,
   "frgn_i60|6m": -0.018,
   "indiv_i20|6m": -0.0718
  },
  "2020-05-14": {
   "frgn_i20|1m": 0.0118,
   "frgn_p20|1m": 0.0063,
   "frgn_i60|1m": 0.0524,
   "indiv_i20|1m": 0.15,
   "frgn_i20|3m": 0.0627,
   "frgn_p20|3m": -0.0148,
   "frgn_i60|3m": 0.0712,
   "indiv_i20|3m": 0.0684,
   "frgn_i20|6m": -0.0899,
   "frgn_p20|6m": -0.1629,
   "frgn_i60|6m": -0.0491,
   "indiv_i20|6m": 0.1768
  },
  "2020-08-11": {
   "frgn_i20|1m": -0.146,
   "frgn_p20|1m": -0.0654,
   "frgn_i60|1m": -0.0937,
   "indiv_i20|1m": -0.0283,
   "frgn_i20|3m": -0.1331,
   "frgn_p20|3m": -0.103,
   "frgn_i60|3m": -0.116,
   "indiv_i20|3m": -0.027,
   "frgn_i20|6m": -0.0837,
   "frgn_p20|6m": -0.093,
   "frgn_i60|6m": -0.0275,
   "indiv_i20|6m": -0.0085
  },
  "2020-11-13": {
   "frgn_i20|1m": 0.0272,
   "frgn_p20|1m": -0.0285,
   "frgn_i60|1m": -0.1084,
   "indiv_i20|1m": -0.0738,
   "frgn_i20|3m": 0.04,
   "frgn_p20|3m": 0.0246,
   "frgn_i60|3m": 0.0107,
   "indiv_i20|3m": 0.036,
   "frgn_i20|6m": -0.065,
   "frgn_p20|6m": -0.0242,
   "frgn_i60|6m": -0.1371,
   "indiv_i20|6m": -0.0121
  },
  "2021-02-17": {
   "frgn_i20|1m": -0.1585,
   "frgn_p20|1m": -0.0683,
   "frgn_i60|1m": -0.1194,
   "indiv_i20|1m": 0.135,
   "frgn_i20|3m": -0.0084,
   "frgn_p20|3m": 0.0464,
   "frgn_i60|3m": 0.0459,
   "indiv_i20|3m": 0.0659,
   "frgn_i20|6m": 0.0257,
   "frgn_p20|6m": 0.0622,
   "frgn_i60|6m": 0.0693,
   "indiv_i20|6m": 0.0237
  },
  "2021-05-20": {
   "frgn_i20|1m": -0.1641,
   "frgn_p20|1m": -0.1435,
   "frgn_i60|1m": -0.201,
   "indiv_i20|1m": 0.1625,
   "frgn_i20|3m": 0.006,
   "frgn_p20|3m": 0.0355,
   "frgn_i60|3m": 0.0045,
   "indiv_i20|3m": 0.1184,
   "frgn_i20|6m": 0.0097,
   "frgn_p20|6m": 0.0082,
   "frgn_i60|6m": -0.0288,
   "indiv_i20|6m": 0.0223
  },
  "2021-08-18": {
   "frgn_i20|1m": 0.0789,
   "frgn_p20|1m": 0.1058,
   "frgn_i60|1m": -0.0258,
   "indiv_i20|1m": -0.0284,
   "frgn_i20|3m": 0.0806,
   "frgn_p20|3m": 0.0925,
   "frgn_i60|3m": 0.0313,
   "indiv_i20|3m": 0.004,
   "frgn_i20|6m": 0.0452,
   "frgn_p20|6m": 0.0186,
   "frgn_i60|6m": -0.0889,
   "indiv_i20|6m": 0.0363
  },
  "2021-11-22": {
   "frgn_i20|1m": -0.0567,
   "frgn_p20|1m": -0.0976,
   "frgn_i60|1m": -0.0271,
   "indiv_i20|1m": 0.0696,
   "frgn_i20|3m": -0.2154,
   "frgn_p20|3m": -0.2261,
   "frgn_i60|3m": -0.0936,
   "indiv_i20|3m": 0.2597,
   "frgn_i20|6m": -0.1661,
   "frgn_p20|6m": -0.1753,
   "frgn_i60|6m": 0.0054,
   "indiv_i20|6m": 0.2946
  },
  "2022-02-24": {
   "frgn_i20|1m": 0.0203,
   "frgn_p20|1m": 0.0499,
   "frgn_i60|1m": -0.0009,
   "indiv_i20|1m": 0.1193,
   "frgn_i20|3m": 0.0058,
   "frgn_p20|3m": 0.0342,
   "frgn_i60|3m": 0.0235,
   "indiv_i20|3m": 0.1131,
   "frgn_i20|6m": 0.0108,
   "frgn_p20|6m": 0.0257,
   "frgn_i60|6m": 0.0059,
   "indiv_i20|6m": 0.1465
  },
  "2022-05-30": {
   "frgn_i20|1m": 0.0325,
   "frgn_p20|1m": 0.0035,
   "frgn_i60|1m": 0.1525,
   "indiv_i20|1m": -0.1039,
   "frgn_i20|3m": -0.0067,
   "frgn_p20|3m": -0.0377,
   "frgn_i60|3m": 0.0867,
   "indiv_i20|3m": -0.0127,
   "frgn_i20|6m": -0.0431,
   "frgn_p20|6m": 0.0343,
   "frgn_i60|6m": 0.0267,
   "indiv_i20|6m": 0.0546
  },
  "2022-08-30": {
   "frgn_i20|1m": 0.1723,
   "frgn_p20|1m": 0.059,
   "frgn_i60|1m": 0.1159,
   "indiv_i20|1m": -0.1531,
   "frgn_i20|3m": -0.0379,
   "frgn_p20|3m": -0.0776,
   "frgn_i60|3m": -0.1152,
   "indiv_i20|3m": 0.0233,
   "frgn_i20|6m": -0.1424,
   "frgn_p20|6m": -0.1552,
   "frgn_i60|6m": -0.2279,
   "indiv_i20|6m": 0.0937
  },
  "2022-12-01": {
   "frgn_i20|1m": -0.075,
   "frgn_p20|1m": -0.0564,
   "frgn_i60|1m": -0.0159,
   "indiv_i20|1m": -0.0117,
   "frgn_i20|3m": 0.0465,
   "frgn_p20|3m": 0.0108,
   "frgn_i60|3m": -0.0164,
   "indiv_i20|3m": -0.0745,
   "frgn_i20|6m": 0.0434,
   "frgn_p20|6m": 0.0588,
   "frgn_i60|6m": -0.0082,
   "indiv_i20|6m": -0.038
  },
  "2023-03-06": {
   "frgn_i20|1m": 0.0393,
   "frgn_p20|1m": 0.0923,
   "frgn_i60|1m": -0.0222,
   "indiv_i20|1m": -0.0349,
   "frgn_i20|3m": 0.0692,
   "frgn_p20|3m": 0.1238,
   "frgn_i60|3m": 0.041,
   "indiv_i20|3m": -0.0253,
   "frgn_i20|6m": 0.0859,
   "frgn_p20|6m": 0.1166,
   "frgn_i60|6m": 0.0953,
   "indiv_i20|6m": -0.058
  },
  "2023-06-07": {
   "frgn_i20|1m": 0.1584,
   "frgn_p20|1m": 0.1285,
   "frgn_i60|1m": 0.1116,
   "indiv_i20|1m": -0.1982,
   "frgn_i20|3m": 0.0085,
   "frgn_p20|3m": 0.0421,
   "frgn_i60|3m": 0.0892,
   "indiv_i20|3m": -0.1133,
   "frgn_i20|6m": 0.0251,
   "frgn_p20|6m": 0.044,
   "frgn_i60|6m": 0.0722,
   "indiv_i20|6m": -0.0851
  },
  "2023-09-05": {
   "frgn_i20|1m": 0.0083,
   "frgn_p20|1m": 0.0762,
   "frgn_i60|1m": 0.0214,
   "indiv_i20|1m": -0.0497,
   "frgn_i20|3m": -0.0344,
   "frgn_p20|3m": 0.0141,
   "frgn_i60|3m": 0.0402,
   "indiv_i20|3m": 0.0412,
   "frgn_i20|6m": 0.0294,
   "frgn_p20|6m": 0.076,
   "frgn_i60|6m": 0.0881,
   "indiv_i20|6m": 0.0069
  },
  "2023-12-08": {
   "frgn_i20|1m": 0.0108,
   "frgn_p20|1m": 0.0668,
   "frgn_i60|1m": 0.0561,
   "indiv_i20|1m": -0.0317,
   "frgn_i20|3m": 0.011,
   "frgn_p20|3m": 0.0213,
   "frgn_i60|3m": 0.0769,
   "indiv_i20|3m": -0.0415,
   "frgn_i20|6m": 0.0542,
   "frgn_p20|6m": 0.057,
   "frgn_i60|6m": 0.1344,
   "indiv_i20|6m": 0.0126
  },
  "2024-03-14": {
   "frgn_i20|1m": -0.0851,
   "frgn_p20|1m": 0.0289,
   "frgn_i60|1m": -0.0327,
   "indiv_i20|1m": 0.2035,
   "frgn_i20|3m": 0.0456,
   "frgn_p20|3m": 0.1422,
   "frgn_i60|3m": 0.0684,
   "indiv_i20|3m": 0.0491,
   "frgn_i20|6m": 0.0788,
   "frgn_p20|6m": 0.1782,
   "frgn_i60|6m": 0.118,
   "indiv_i20|6m": -0.203
  },
  "2024-06-18": {
   "frgn_i20|1m": -0.022,
   "frgn_p20|1m": -0.0738,
   "frgn_i60|1m": 0.0696,
   "indiv_i20|1m": 0.1416,
   "frgn_i20|3m": -0.0504,
   "frgn_p20|3m": -0.063,
   "frgn_i60|3m": -0.0384,
   "indiv_i20|3m": 0.1596,
   "frgn_i20|6m": -0.0001,
   "frgn_p20|6m": 0.0019,
   "frgn_i60|6m": -0.0108,
   "indiv_i20|6m": 0.0947
  },
  "2024-09-19": {
   "frgn_i20|1m": -0.0765,
   "frgn_p20|1m": -0.0178,
   "frgn_i60|1m": -0.0815,
   "indiv_i20|1m": 0.0209,
   "frgn_i20|3m": 0.0111,
   "frgn_p20|3m": 0.0379,
   "frgn_i60|3m": -0.015,
   "indiv_i20|3m": -0.0572,
   "frgn_i20|6m": 0.0047,
   "frgn_p20|6m": 0.0312,
   "frgn_i60|6m": -0.0723,
   "indiv_i20|6m": 0.0136
  },
  "2024-12-20": {
   "frgn_i20|1m": -0.0533,
   "frgn_p20|1m": -0.0586,
   "frgn_i60|1m": 0.078,
   "indiv_i20|1m": 0.0719,
   "frgn_i20|3m": -0.0179,
   "frgn_p20|3m": -0.0612,
   "frgn_i60|3m": 0.0636,
   "indiv_i20|3m": 0.0177,
   "frgn_i20|6m": 0.033,
   "frgn_p20|6m": -0.0399,
   "frgn_i60|6m": 0.1242,
   "indiv_i20|6m": 0.0264
  },
  "2025-03-31": {
   "frgn_i20|1m": -0.0319,
   "frgn_p20|1m": -0.0174,
   "frgn_i60|1m": 0.0802,
   "indiv_i20|1m": 0.041,
   "frgn_i20|3m": 0.0251,
   "frgn_p20|3m": -0.0328,
   "frgn_i60|3m": 0.1362,
   "indiv_i20|3m": -0.0493,
   "frgn_i20|6m": -0.0004,
   "frgn_p20|6m": 0.0063,
   "frgn_i60|6m": 0.029,
   "indiv_i20|6m": 0.0268
  }
 }
}