{
  "holdings": {
    "024110": {
      "since": "2026-07-21",
      "entry_price": 21803.0,
      "peak": 21803.0,
      "armed": true
    },
    "006040": {
      "since": "2026-07-21",
      "entry_price": 33405.0,
      "peak": 34350.0,
      "armed": true
    },
    "071320": {
      "since": "2026-07-21",
      "entry_price": 65709.0,
      "peak": 65709.0,
      "armed": true
    },
    "139480": {
      "since": "2026-07-21",
      "entry_price": 79910.0,
      "peak": 83400.0,
      "armed": true
    },
    "002030": {
      "since": "2026-07-21",
      "entry_price": 176223.0,
      "peak": 182300.0,
      "armed": true
    }
  },
  "last_run": "2026-07-23"
}