{
  "input": {
    "horizon": "6m",
    "universe": "kospi200_pit",
    "cost": "kospi: 매수 6.5bp + 매도 26.50bp (왕복 33.00bp)"
  },
  "n_trials": 211,
  "n_events": 26,
  "pbo": {
    "pbo": 0.1477,
    "embargo": 1,
    "purged_events_total": 5544,
    "n_combos": 907,
    "n_blocks": 12,
    "lambda_mean": 1.6304,
    "is_sharpe_mean": 0.6085,
    "oos_sharpe_mean": 0.2072,
    "degradation_slope": -1.114,
    "prob_oos_loss": 0.3153
  },
  "pbo_verdict": "낮음(과최적화 가능성 작음)",
  "dsr": {
    "sr": 0.5386,
    "sr0": 0.319,
    "dsr": 0.7453,
    "dsr_uncorrected": 0.8295,
    "skew": -0.446,
    "kurtosis": 2.239,
    "T": 26,
    "T_eff": 13,
    "N": 211,
    "best_trial": "frgn_flow2·pbr_inv1"
  },
  "dsr_verdict": "통과 실패(다중검정 감안 시 샤프가 유의하지 않음)",
  "passed": false,
  "references": [
    "Bailey et al. 2017 (PBO/CSCV)",
    "Bailey & López de Prado 2014 (DSR)"
  ],
  "note": "조합 간 상관으로 N이 과대계상될 수 있어 DSR은 보수적(실제보다 낮게) 추정됨."
}